get_job_list/__init__.py
get_job_list/conversion.py
get_job_list/scraping.py
job_scraper/__init__.py
job_scraper/conversion.py
job_scraper/scraping.py
jb_scraper-0.1.2.dist-info/METADATA
jb_scraper-0.1.2.dist-info/WHEEL
jb_scraper-0.1.2.dist-info/top_level.txt
jb_scraper-0.1.2.dist-info/RECORD
