Metadata-Version: 2.4
Name: jb-scraper
Version: 0.1.2
Summary: JobScraper, um pacote de raspagem de vagas na internet.
Home-page: https://github.com/ClausAlaerth/jobscraper-package
Author: Lucas Aquino
Author-email: lc.aquinodeoliveira@gmail.com
Requires-Python: >=3.12
Requires-Dist: attrs==25.3.0
Requires-Dist: certifi==2025.1.31
Requires-Dist: cffi==1.17.1
Requires-Dist: charset-normalizer==3.4.1
Requires-Dist: et_xmlfile==2.0.0
Requires-Dist: h11==0.14.0
Requires-Dist: idna==3.10
Requires-Dist: mypy==1.15.0
Requires-Dist: mypy-extensions==1.0.0
Requires-Dist: openpyxl==3.1.5
Requires-Dist: openpyxl-stubs==0.1.25
Requires-Dist: outcome==1.3.0.post0
Requires-Dist: packaging==24.2
Requires-Dist: pycparser==2.22
Requires-Dist: PySocks==1.7.1
Requires-Dist: python-dotenv==1.1.0
Requires-Dist: requests==2.32.3
Requires-Dist: selenium==4.30.0
Requires-Dist: sniffio==1.3.1
Requires-Dist: sortedcontainers==2.4.0
Requires-Dist: trio==0.29.0
Requires-Dist: trio-websocket==0.12.2
Requires-Dist: typing_extensions==4.13.0
Requires-Dist: urllib3==2.3.0
Requires-Dist: webdriver-manager==4.0.2
Requires-Dist: websocket-client==1.8.0
Requires-Dist: wsproto==1.2.0
Dynamic: author
Dynamic: author-email
Dynamic: description
Dynamic: description-content-type
Dynamic: home-page
Dynamic: requires-dist
Dynamic: requires-python
Dynamic: summary
